{
  "metadata": {
    "source_pdf": "template_8\\4_4950_9812013903228.pdf",
    "template": 8,
    "extraction_method": "Text"
  },
  "raw_extracted": {
    "full_text": "1/32/10/98/01/99/00200 0006720 :­YfYÃZ1⁄4 :ÊËZZÀ :\\¿xËZe 1381/05/15 :dÌ·Z §Â¿ :dÌ·Z §| ̄ :Ä¿YÁaÉZ¬¿YxËZe 1425/01/01 ÄÌ·ÁY :ÄË~¤eZf·Á 43021⁄2| »Ád À :Ä§ e| ̄Á1⁄2YÂÀ :^«ÄZÀ 9812013903228 :ÂfÀ ̄Ä¿|]ÃZ1⁄4 1859477000419 ®»1⁄2| » ­YYÃ{ZmËÔ» :¥»¶v»Ê¿Z¿ :ÊeZ^eZ°»¶v»Ê¿Z¿ :Ê ̧»ÄZÀ :É{Zf«Y| ̄ :Êfa| ̄ :1fv»­f» ÄÀ ́¿ 2ËÔ»©]ËÂe 2ËÔ»©]ËÂe :Â»Y Æ : {M :©]Ä¬À» :g{YÂu|uYÁ 121 1⁄2Y|1⁄4Å1⁄2ZfY©]ÉÁÌ¿ËÂe www.edch.ir w¿ 5Ã{Z» 16Ã{Z» w¿j ̄Y|uZ]¢ ̧^» μZËYZ] Á{Â ̧]Zew¿Z]¢ ̧^» μZË Ä§ ew¿Z]¢ ̧^» μZË YZ]w¿j ̄Y|u Á{Â ̧]Zew¿ Ä§ ew¿ μZË¢ ̧^» w¿ μÂ1⁄4»É¿Y μZË¢ ̧^» w¿ μÂ1⁄4»É¿Y ¥Z»s 2441559767 48418905056 3641366969 0 0 5490 0 0 0 1,207,879,230 60703 19898/2 ÉZ]1⁄2ZÌ» 1123596386 19988725607 3006523386 0 0 10980 0 0 0 498,647,511 60703 8214/5 ÉZ]kÁY 1252267216 27155997737 1021139915 0 0 2745 0 0 0 677,445,424 60703 11160 ÉZ]o ̄ 0 0 0 0 0 0 0 0 0 0 0 Ä 1⁄4mZ]kÁY ËZ YZ]kZyÉZ°¿Zf] cY¬»ÉYmYcÁZ ̈f·YÄ]Z» Ä°^®·Z»ÂeÃ|Ê¿Z^Ìfa μZË¢ ̧^» w¿ μÂ1⁄4»É¿Y YÂÁÂÌf ̄Y ©] μZË¢ ̧^» w¿ μÂ1⁄4»É¿Y μZË¢ ̧^» w¿ μÂ1⁄4»É¿Y μZË¢ ̧^» w¿ μÂ1⁄4»É¿Y ¥Z»s 3078806867 4785/4 643374/5 1103752 1190/25 927/3 1741057600 2624/95 663272/7 0 4785/4 0 ÉZ]1⁄2ZÌ» 1416855043 5334/47 265603/6 1168636 1190/25 981/8 2222020669 8114/95 273818/2 0 5334/47 0 ÉZ]kÁY 1579108959 4376/2 360840 14283037 1190/25 12000 0 0 0 0 4376/2 0 ÉZ]o ̄ 0 0 0 0 0 0 0 0 0 0 0 0 Ä 1⁄4mZ]kÁY 0 0 0 556,952,681 0 3,963,078,270 16,555,425 2,383,972,165 1,516,352,144 688,758,655 6,887,586,543 0 510 c|«ÉZÆ] Ä¿YÁaZ^fYÉZ¬¿YcÁZ ̈e ÊÅZ3ÁÌ¿dyÂÄÀËÅ Ã|3⁄4Ì»ZeÉ¿YÉZÆ] 16Ã{Z»É¿YÉZÆ] cY¬»ÉYmYcÁZ ̈f·YÄ]Z» YZ]kZy|ËyÉZ°¿Zf] ©]YÂ YÂÁcZÌ·Z» ÃÁ{©]ÉZÆ] Ë~a|Ë|neY3⁄4Ì»PecÁZ ̈f·YÄ]Z» μZËYÅ ̄ 1⁄2Z1⁄4¿Â]MÉZÆ] 138,853 ÉZ°Å|] 11,870,475,168 c|«YÁZne Äf~3ÉZÅÃÁ{ÉZÅdyY{aÁ¢·Z^»,¥Z»a]YÂ ÃÁ{¢ ̧^» ÂÌf ̄Y Ä 1⁄4mZ]kÁY ÉZ]o ̄ ÉZ]kÁY ÉZ]1⁄2ZÌ» dWY«xËZe ÃÁ{ 10953791129 481855 0 487090 242727 761999 04/02/01 1404/02 12905061263 519927 0 500181 235636 715636 04/03/01 1404/03 13227554110 631473 0 449454 256363 683999 04/04/01 1404/04 7246151766 559091 0 281454 285818 571636 04/05/01 1404/05 6619934279 407727 0 275454 234545 499090 04/06/01 1404/06 5859040691 94964 0 224727 206181 431999 04/07/01 1404/07 4950.00 2781/82 :Zn» :Ê§» :É{Y{Y« :f1⁄4Ì ̄Z» 0/0510 4455/00 0 :Äf§ZËÅZ ̄ :c|«YÁZne1⁄2YÌ» :Ã|Ä^Zv» cYÁÂ ̧Ì ̄c|« :1⁄2ZËm¿Ye\\Ë 54545.45 :dWY«\\Ë 1404/07/01 30 1404/08/12 :ÃÁ{Á{Y| e :[ZveÂÁ|xËZe :xËZeY :μZ ÃÁ{ 1404/07 1404/08/01 :xËZeZe 0 :1⁄2ZË\\Ë 100/42219/14/03ÃZ1⁄4Ä]Â»ÉYmY,1404/04/17wÂ»140431390000864126ÃZ1⁄4Ä]ÉY{Yd·Y|1⁄2YÂË{1fv»Ê»Â1⁄4dXÌÅÄ»Z¿{Y{ÄmÂeZ]Ê»Y3­f» |Z]Ê»d§ZË{¶]Z¬·ZË11,902,030,885¢ ̧^»Ä]É¿YÂ^«{d«Â»Ç| ̄¢·Z^»Á¿Z»Ô]1403/07/01xËZe. |Z]Ê»μZË11870475168[ZveÂÁ|Y¶^«Z1⁄4ÉZ°Å|] 4111-7997-5767 :Ê ̧»ÄZÀ :É{Zf«Y| ̄ ÉÂ§ dyY{ad ̧Æ» Ê§»©]^«ÄZÀ 9812013903228 2096317247245 dyY{aÄZÀ 20,963,172,000 dyY{a¶]Z«¢ ̧^» Ã|dWY«É¿Y ¢ ̧^» ¶ ̄¥» Ê¿ÂÀ ̄Ã|¿Z1⁄4 Ê ̧^«Ã|¿Z1⁄4 ¥Z»s 3,641,366,969 663272/67/20 4295/98 4283/82 ÉZ]1⁄2ZÌ» 3,006,523,386 273818/15/90 1432/09 1427/07 ÉZ]kÁY 1,021,139,915 371999/96/90 2784/78 2777/96 ÉZ]o ̄ 0/0000 0/00 0/00 Ä 1⁄4mZ]kÁY 401399/96/66 677/65 670/29 ÂÌf ̄Y É{Z|Ëy ^|Ëy Ë~a|Ë|neYÃ|3⁄4Ì»Ze ÊËÂmÄ§ÊÅYÂ3 É¿Y Â] Ä^¿ZmÁ{ Â] Ä^¿ZmÁ{ 0 0 664200 0 0 0 0 0 274800 0 0 0 0 0 384000 0 0 0 0 0 0 0 0 0 0 0 0 0 0 0 1,949,716,000 dyY{a¶]Z«¢ ̧^» dË¿Ye^«ÄZÀ 9812013983221 dË¿YeÉZÆ] ÉZ°¿Zf] ÉZ°Å|] μZËYÅ ̄ 711 -347,119,097 2,088,032,553 Ã{Á§YY]cZÌ·Z» 208,803,255 0194971647217 dyY{aÄZÀ dyY{a¢ ̧^» dyY{ad ̧Æ» ÃÁ{¢ ̧^» dWY«xËZe μÂ1⁄4»c|« ÃÁ{ 1673888000 04/05/04 1673888260 04/02/01 1404/02 1723550000 04/03/20 1723550256 04/03/01 1404/03 04/08/14 1964424106 04/04/01 1404/04 4268119000 04/08/14 2132970447 04/05/01 1404/05 2320655000 04/08/14 2227828652 04/06/01 1404/06 2089219000 04/08/14 2005650035 04/07/01 1404/07 ÉÂ§ dyY{ad ̧Æ» dË¿YeμÂ1⁄4»c|« dË¿YeÄ¿ZÌÅZ»w¿ 750,600 2,782",
    "_source_pdf": "template_8\\4_4950_9812013903228.pdf"
  },
  "structured_data": {
    "metadata": {
      "source_pdf": "8.pdf",
      "template": 8,
      "extraction_method": "Text",
      "extraction_timestamp": "2025-12-06T11:53:18.538296",
      "template_config_version": "8.0",
      "extractor_version": "2.0",
      "note": "Template 8 has no consumption table - unique structure"
    },
    "account_info": {
      "bill_id": "9812013903228",
      "payment_id": "2096317247245"
    },
    "bill_header": {
      "bill_id": "9812013903228",
      "payment_id": "2096317247245"
    },
    "billing_period": {},
    "power_capacity": {},
    "energy_charges": {
      "charges": {
        "supplied_energy_cost": {
          "amount": 11870475168,
          "label": "بهای انرژی تامین شده"
        }
      },
      "subtotal_energy": 11870475168,
      "note": "No per-period breakdown available in this template"
    },
    "additional_charges": {
      "subscription_fee": {
        "amount": 138853,
        "label": "بهای آبونمان"
      },
      "fuel_cost": 750600,
      "tariff_difference": 16555425,
      "subtotal_charges": 17444878,
      "subscription": 138853,
      "vat": 1404
    },
    "transit_costs": {
      "transit_vat": 1404,
      "transit_vat_label": "مالیات بر ارزش افزوده",
      "total": 1404
    },
    "financial_summary": {
      "energy_charges_total": 11870475168,
      "additional_charges_total": 17444878,
      "period_subtotal": 0,
      "transit_costs_total": 1404,
      "balance": 0,
      "grand_total": 20963172000,
      "currency": "IRR",
      "amount_payable": 20963172000
    },
    "_statistics": {
      "total_fields_extracted": 31,
      "sections": 9,
      "completeness_percentage": 75,
      "template_note": "Template 8 is unique - no consumption table",
      "critical_fixes": [
        "Fixed malformed period dates",
        "Separated transit costs into dedicated section",
        "Created energy charges from cost breakdown",
        "Implemented V2.0 structure (8 sections available)"
      ]
    },
    "_original_structured": {
      "power_info": {},
      "cost_breakdown": {
        "power_cost": 688758655,
        "power_cost_label": "بهای قدرت",
        "subscription_fee": 138853,
        "subscription_fee_label": "بهای آبونمان",
        "fuel_cost": 750600,
        "fuel_cost_label": "هزینه سوخت نیروگاهی",
        "tariff_difference": 16555425,
        "tariff_difference_label": "مابه التفاوت اجرای مقررات",
        "supplied_energy_cost": 11870475168,
        "supplied_energy_cost_label": "بهای انرژی تامین شده"
      },
      "final_charges": {
        "payable_amount": 20963172000,
        "payable_amount_label": "مبلغ قابل پرداخت",
        "vat": 1404,
        "vat_label": "مالیات بر ارزش افزوده"
      },
      "period_info": {},
      "account_info": {
        "bill_id": "9812013903228",
        "payment_id": "2096317247245"
      }
    }
  }
}